<screen name="EPGSelectionEPGBar_HD" backgroundColor="transparent" flags="wfNoBorder" position="0,640" size="1920,440" NoAnimationAfter="1">
  <!-- Backgrounds -->
  <constant-widget name="background_window" />
  <ePixmap pixmap="MetrixReloaded/buttons/red.png" position="100,338" size="31,31" alphatest="blend" />
  <ePixmap pixmap="MetrixReloaded/buttons/green.png" position="470,338" size="31,31" alphatest="blend" />
  <ePixmap pixmap="MetrixReloaded/buttons/yellow.png" position="840,338" size="31,31" alphatest="blend" />
  <ePixmap pixmap="MetrixReloaded/buttons/blue.png" position="1210,338" size="31,31" alphatest="blend" />
  <widget font="Regular;30" halign="left" valign="center" name="key_red" position="140,321" size="250,60" zPosition="1" backgroundColor="infobarBgR" transparent="1" />
  <widget font="Regular;30" halign="left" valign="center" name="key_green" position="510,321" size="250,60" zPosition="1" backgroundColor="infobarBgR" transparent="1" />
  <widget font="Regular;30" halign="left" valign="center" name="key_yellow" position="880,321" size="250,60" zPosition="1" backgroundColor="infobarBgR" transparent="1" />
  <widget font="Regular;30" halign="left" valign="center" name="key_blue" position="1250,321" size="250,60" zPosition="1" backgroundColor="infobarBgR" transparent="1" />
  <widget name="list" position="100,60" size="825,252" itemHeight="36" backgroundColorRows="listBackgroundBarsOne" backgroundColor="infobarBgR" transparent="1" scrollbarMode="showAlways" scrollbarBackgroundPicture="MetrixReloaded/media/scrollbar_bg.png" scrollbarWidth="6" scrollbarSliderBorderWidth="0" scrollbarKeepGapColor="1" scrollbarGap="20" enableWrapAround="1" />
  <widget font="Regular;30" backgroundColor="infobarBgR" position="945,60" size="545,246" render="Label" source="Event" transparent="1">
    <convert type="EventName">FullDescription</convert>
  </widget>
  <widget alphatest="blend" position="1588,120" render="Picon" size="220,132" source="Service" zPosition="1">
    <convert type="ServiceName">Reference</convert>
  </widget>
  <widget font="Bold;38" foregroundColor="accentColorOne" valign="center" halign="center" position="1539,270" render="Label" size="320,100" backgroundColor="infobarBgR" source="Service" zPosition="1" transparent="1">
    <convert type="ServiceName">Name</convert>
  </widget>
  <ePixmap pixmap="MetrixReloaded/media/icons/clock.png" position="1625,65" zPosition="1" size="31,31" alphatest="blend" />
  <widget source="global.CurrentTime" render="Label" position="1665,60" zPosition="1" size="100,40" font="Bold; 38" halign="right" valign="center" backgroundColor="infobarBgR" transparent="1">
    <convert type="ClockToText">Format:%H:%M</convert>
  </widget>
  <widget text="EPGSelectionEPGBar_HD" render="MetrixReloadedScreenNameLabel" size="200,25" valign="center" halign="right" font="SetrixSL;16" foregroundColor="foreground" backgroundColor="#2d000000" source="Title" position="1720,415" />
</screen>